astrodynx/__init__.py
astrodynx/_version.py
astrodynx/diffeq/__init__.py
astrodynx/events/__init__.py
astrodynx/events/radius.py
astrodynx/gravity/__init__.py
astrodynx/gravity/_general.py
astrodynx/prop/__init__.py
astrodynx/prop/_cowell_method.py
astrodynx/prop/_kepler.py
astrodynx/twobody/__init__.py
astrodynx/twobody/_kep_equ.py
astrodynx/twobody/_lagrange.py
astrodynx/twobody/_orb_elements.py
astrodynx/twobody/_orb_integrals.py
astrodynx/twobody/_path_check.py
astrodynx/twobody/_state_trans.py
astrodynx/twobody/_uniformulas.py
astrodynx/utils/__init__.py
astrodynx/utils/_rot_mat.py
astrodynx-0.9.12.dist-info/licenses/LICENSE
astrodynx-0.9.12.dist-info/METADATA
astrodynx-0.9.12.dist-info/WHEEL
astrodynx-0.9.12.dist-info/top_level.txt
astrodynx-0.9.12.dist-info/RECORD
