Metadata-Version: 2.4
Name: astrodynx
Version: 0.9.12
Summary: A modern astrodynamics library powered by JAX.
Author-email: Peng SHU <pennbay@outlook.com>
License-Expression: MIT
Project-URL: Homepage, https://github.com/adxorg/astrodynx
Project-URL: Bug Tracker, https://github.com/adxorg/astrodynx/issues
Project-URL: Documentation, https://astrodynx.readthedocs.io
Keywords: astrodynamics,celestial mechanics
Classifier: Intended Audience :: Science/Research
Classifier: Programming Language :: Python :: 3
Classifier: Programming Language :: Python :: 3.10
Classifier: Programming Language :: Python :: 3.11
Classifier: Programming Language :: Python :: 3.12
Classifier: Operating System :: OS Independent
Classifier: Topic :: Scientific/Engineering :: Astronomy
Classifier: Topic :: Scientific/Engineering :: Physics
Requires-Python: >=3.10
License-File: LICENSE
Requires-Dist: jax>=0.7.0
Requires-Dist: equinox>=0.13.0
Requires-Dist: diffrax>=0.7.0
Provides-Extra: dev
Requires-Dist: commitizen; extra == "dev"
Requires-Dist: pytest; extra == "dev"
Requires-Dist: pytest-cov; extra == "dev"
Requires-Dist: pre-commit; extra == "dev"
Provides-Extra: docs
Requires-Dist: sphinx; extra == "docs"
Requires-Dist: sphinx-book-theme; extra == "docs"
Requires-Dist: myst-parser; extra == "docs"
Requires-Dist: nbsphinx; extra == "docs"
Requires-Dist: sphinx-autodoc-typehints; extra == "docs"
Requires-Dist: sphinx-copybutton; extra == "docs"
Requires-Dist: sphinx-math-dollar; extra == "docs"
Requires-Dist: ipython; extra == "docs"
Requires-Dist: matplotlib; extra == "docs"
Requires-Dist: jupyter; extra == "docs"
Dynamic: license-file
